cognite/air_ds_util/__init__.py
cognite/air_ds_util/air_model_utils.py
cognite/air_ds_util/scheduling.py
cognite/air_ds_util/utils.py
cognite_air_ds_util-0.3.7.dist-info/LICENSE
cognite_air_ds_util-0.3.7.dist-info/WHEEL
cognite_air_ds_util-0.3.7.dist-info/METADATA
cognite_air_ds_util-0.3.7.dist-info/RECORD
